ggpy
