Metadata-Version: 1.1
Name: ggpy
Version: 0.1.2
Summary: ggplot2 from your command line
Home-page: http://github.com/premisedata/ggpy
Author: Sammy Nammari, Daniel Duckworth
Author-email: sammy.nammari@gmail.com, duckworthd@gmail.com
License: BSD
Keywords: plot visualization plotting ggplot2
Platform: UNKNOWN
Classifier: Development Status :: 4 - Beta
Classifier: Intended Audience :: Science/Research
Classifier: Intended Audience :: System Administrators
Classifier: License :: OSI Approved :: BSD License
Classifier: Programming Language :: Python
Classifier: Topic :: Scientific/Engineering :: Visualization
Classifier: Operating System :: Unix
Classifier: Operating System :: MacOS
